{"trial_id": "a4f98f5dbf88d9ee2169a26241ac4d1c", "hyperparameters": {"space": [{"class_name": "Int", "config": {"name": "units", "default": 50, "min_value": 50, "max_value": 100, "step": 25, "sampling": null}}, {"class_name": "Float", "config": {"name": "dropout", "default": 0.25, "min_value": 0.0, "max_value": 0.33, "step": null, "sampling": null}}, {"class_name": "Choice", "config": {"name": "learning_rate", "default": 0.0, "values": [0.0, 0.01, 0.001, 0.0001], "ordered": true}}], "values": {"units": 50, "dropout": 0.303229335518561, "learning_rate": 0.01}}, "metrics": {"metrics": {"loss": {"direction": "min", "observations": [{"value": [108.51584167480469], "step": 0}]}, "mean_absolute_error": {"direction": "min", "observations": [{"value": [108.5158462524414], "step": 0}]}, "mean_absolute_percentage_error": {"direction": "min", "observations": [{"value": [270694.9375], "step": 0}]}, "mean_squared_error": {"direction": "min", "observations": [{"value": [20454.662109375], "step": 0}]}, "val_loss": {"direction": "min", "observations": [{"value": [90.72124786376953], "step": 0}]}, "val_mean_absolute_error": {"direction": "min", "observations": [{"value": [90.72125244140625], "step": 0}]}, "val_mean_absolute_percentage_error": {"direction": "min", "observations": [{"value": [72.18223571777344], "step": 0}]}, "val_mean_squared_error": {"direction": "min", "observations": [{"value": [14429.625], "step": 0}]}}}, "score": 90.72125244140625, "best_step": 0, "status": "COMPLETED"}