{"trial_id": "08", "hyperparameters": {"space": [{"class_name": "Int", "config": {"name": "units", "default": 30, "conditions": [], "min_value": 10, "max_value": 50, "step": 10, "sampling": "linear"}}, {"class_name": "Float", "config": {"name": "dropout", "default": 0.25, "conditions": [], "min_value": 0.0, "max_value": 0.33, "step": null, "sampling": "linear"}}, {"class_name": "Choice", "config": {"name": "learning_rate", "default": 0.0, "conditions": [], "values": [0.0, 0.01, 0.001, 0.0001], "ordered": true}}], "values": {"units": 30, "dropout": 0.14640395076312407, "learning_rate": 0.001}}, "metrics": {"metrics": {"loss": {"direction": "min", "observations": [{"value": [0.21557939797639847], "step": 55}]}, "mean_absolute_error": {"direction": "min", "observations": [{"value": [0.21557939797639847], "step": 55}]}, "rmse": {"direction": "min", "observations": [{"value": [0.272145539522171], "step": 55}]}, "val_loss": {"direction": "min", "observations": [{"value": [0.2681823670864105], "step": 55}]}, "val_mean_absolute_error": {"direction": "min", "observations": [{"value": [0.2681823670864105], "step": 55}]}, "val_rmse": {"direction": "min", "observations": [{"value": [0.31960421800613403], "step": 55}]}}}, "score": 0.2681823670864105, "best_step": 55, "status": "COMPLETED", "message": null}