{"trial_id": "6c0e0eda90075a732c058699220da3dd", "hyperparameters": {"space": [{"class_name": "Int", "config": {"name": "units", "default": 30, "min_value": 10, "max_value": 50, "step": 10, "sampling": null}}, {"class_name": "Float", "config": {"name": "dropout", "default": 0.25, "min_value": 0.0, "max_value": 0.33, "step": null, "sampling": null}}, {"class_name": "Choice", "config": {"name": "learning_rate", "default": 0.0, "values": [0.0, 0.01, 0.001, 0.0001], "ordered": true}}], "values": {"units": 40, "dropout": 0.19336999939349597, "learning_rate": 0.01}}, "metrics": {"metrics": {"loss": {"direction": "min", "observations": [{"value": [0.09755997955799103], "step": 0}]}, "mean_absolute_error": {"direction": "min", "observations": [{"value": [0.09755997359752655], "step": 0}]}, "rmse": {"direction": "min", "observations": [{"value": [0.13700677454471588], "step": 0}]}, "val_loss": {"direction": "min", "observations": [{"value": [0.20692962408065796], "step": 0}]}, "val_mean_absolute_error": {"direction": "min", "observations": [{"value": [0.20692963898181915], "step": 0}]}, "val_rmse": {"direction": "min", "observations": [{"value": [0.2556856572628021], "step": 0}]}}}, "score": 0.20692963898181915, "best_step": 0, "status": "COMPLETED"}