{"trial_id": "3bec4f2a62c78d0ce897b8a5e61ad576", "hyperparameters": {"space": [{"class_name": "Int", "config": {"name": "units", "default": 30, "min_value": 10, "max_value": 50, "step": 10, "sampling": null}}, {"class_name": "Float", "config": {"name": "dropout", "default": 0.25, "min_value": 0.0, "max_value": 0.33, "step": null, "sampling": null}}, {"class_name": "Choice", "config": {"name": "learning_rate", "default": 0.0, "values": [0.0, 0.01, 0.001, 0.0001], "ordered": true}}], "values": {"units": 40, "dropout": 0.12566896859404217, "learning_rate": 0.001}}, "metrics": {"metrics": {"loss": {"direction": "min", "observations": [{"value": [0.13309602439403534], "step": 0}]}, "mean_absolute_error": {"direction": "min", "observations": [{"value": [0.13309602439403534], "step": 0}]}, "rmse": {"direction": "min", "observations": [{"value": [0.1738780289888382], "step": 0}]}, "val_loss": {"direction": "min", "observations": [{"value": [0.19123602658510208], "step": 0}]}, "val_mean_absolute_error": {"direction": "min", "observations": [{"value": [0.19123601913452148], "step": 0}]}, "val_rmse": {"direction": "min", "observations": [{"value": [0.23188933730125427], "step": 0}]}}}, "score": 0.19123601913452148, "best_step": 0, "status": "COMPLETED"}