{"trial_id": "ed675831158dee67f67a25a4c35acb00", "hyperparameters": {"space": [{"class_name": "Int", "config": {"name": "units", "default": 30, "min_value": 10, "max_value": 50, "step": 10, "sampling": null}}, {"class_name": "Float", "config": {"name": "dropout", "default": 0.25, "min_value": 0.0, "max_value": 0.33, "step": null, "sampling": null}}, {"class_name": "Choice", "config": {"name": "learning_rate", "default": 0.0, "values": [0.0, 0.01, 0.001, 0.0001], "ordered": true}}], "values": {"units": 30, "dropout": 0.17058352143065617, "learning_rate": 0.0}}, "metrics": {"metrics": {"loss": {"direction": "min", "observations": [{"value": [0.47594909369945526], "step": 0}]}, "mean_absolute_error": {"direction": "min", "observations": [{"value": [0.47594910860061646], "step": 0}]}, "rmse": {"direction": "min", "observations": [{"value": [0.545169472694397], "step": 0}]}, "val_loss": {"direction": "min", "observations": [{"value": [0.6354897320270538], "step": 0}]}, "val_mean_absolute_error": {"direction": "min", "observations": [{"value": [0.6354897022247314], "step": 0}]}, "val_rmse": {"direction": "min", "observations": [{"value": [0.6950753331184387], "step": 0}]}}}, "score": 0.6354897022247314, "best_step": 0, "status": "COMPLETED"}