{"ongoing_trials": {}, "hyperparameters": {"space": [{"class_name": "Int", "config": {"name": "units", "default": 30, "min_value": 10, "max_value": 50, "step": 10, "sampling": null}}, {"class_name": "Float", "config": {"name": "dropout", "default": 0.25, "min_value": 0.0, "max_value": 0.33, "step": null, "sampling": null}}, {"class_name": "Choice", "config": {"name": "learning_rate", "default": 0.0, "values": [0.0, 0.01, 0.001, 0.0001], "ordered": true}}], "values": {"units": 30, "dropout": 0.25, "learning_rate": 0.0}}, "seed": 2109, "seed_state": 2115, "tried_so_far": ["1f68bf0b0802b64d7fc06d69d2a5a9c8", "e0e98c8171f94ba0c176c9cb625ec7af"]}